setup.py
gclid_timestamp_decoder/__init__.py
gclid_timestamp_decoder/decode.py
gclid_timestamp_decoder/gclid_pb2.py
gclid_timestamp_decoder.egg-info/PKG-INFO
gclid_timestamp_decoder.egg-info/SOURCES.txt
gclid_timestamp_decoder.egg-info/dependency_links.txt
gclid_timestamp_decoder.egg-info/requires.txt
gclid_timestamp_decoder.egg-info/top_level.txt