Metadata-Version: 1.1
Name: gclid-timestamp-decoder
Version: 0.1.2
Summary: Decoding timestamp from Google gclid using Protocol Buffers.
Home-page: https://github.com/qoelet/gclid-timestamp-decoder
Author: Kenny Shen
Author-email: kenny@machinesung.com
License: BSD
Download-URL: https://pypi.python.org/pypi/gclid-timestamp-decoder
Platform: UNKNOWN
